<?xml version="1.0" encoding="UTF-8"?>
<!DOCTYPE plist PUBLIC "-//Apple//DTD PLIST 1.0//EN" "http://www.apple.com/DTDs/PropertyList-1.0.dtd"/>

<plist version="1.0">
    <dict>
        <key>ROOT</key>
        <array>
            <dict>
                <key>id</key>
                <string>114</string>
                <key>className</key>
                <string>PTModelObjectImage</string>
                <key>Name</key>
                <dict>
                    <key>value</key>
                    <string>Untitled</string>
                </dict>
                <key>Position</key>
                <dict>
                    <key>value</key>
                    <string>{0.000,0.000}</string>
                </dict>
                <key>Scale</key>
                <dict>
                    <key>value</key>
                    <string>{1.000,1.000}</string>
                </dict>
                <key>Hidden</key>
                <dict>
                    <key>visible</key>
                    <string>0</string>
                </dict>
                <key>Locked</key>
                <dict>
                    <key>visible</key>
                    <string>0</string>
                </dict>
                <key>Stick To Edge</key>
                <dict>
                    <key>value</key>
                    <string>0</string>
                </dict>
                <key>zDepth</key>
                <string>0</string>
            </dict>
            <dict>
                <key>id</key>
                <string>155</string>
                <key>className</key>
                <string>PTModelObjectImage</string>
                <key>Name</key>
                <dict>
                    <key>value</key>
                    <string>Untitled</string>
                </dict>
                <key>Position</key>
                <dict>
                    <key>value</key>
                    <string>{0.000,0.000}</string>
                </dict>
                <key>Scale</key>
                <dict>
                    <key>value</key>
                    <string>{1.000,1.000}</string>
                </dict>
                <key>Hidden</key>
                <dict>
                    <key>visible</key>
                    <string>0</string>
                </dict>
                <key>Locked</key>
                <dict>
                    <key>visible</key>
                    <string>0</string>
                </dict>
                <key>Stick To Edge</key>
                <dict>
                    <key>value</key>
                    <string>0</string>
                </dict>
                <key>zDepth</key>
                <string>0</string>
            </dict>
            <dict>
                <key>id</key>
                <string>346</string>
                <key>className</key>
                <string>PTModelObjectImage</string>
                <key>Name</key>
                <dict>
                    <key>value</key>
                    <string>Untitled</string>
                </dict>
                <key>Position</key>
                <dict>
                    <key>value</key>
                    <string>{0.000,0.000}</string>
                </dict>
                <key>Scale</key>
                <dict>
                    <key>value</key>
                    <string>{1.000,1.000}</string>
                </dict>
                <key>Hidden</key>
                <dict>
                    <key>visible</key>
                    <string>0</string>
                </dict>
                <key>Locked</key>
                <dict>
                    <key>visible</key>
                    <string>0</string>
                </dict>
                <key>Stick To Edge</key>
                <dict>
                    <key>value</key>
                    <string>0</string>
                </dict>
                <key>zDepth</key>
                <string>0</string>
            </dict>
            <dict>
                <key>id</key>
                <string>447</string>
                <key>className</key>
                <string>PTModelObjectImage</string>
                <key>Name</key>
                <dict>
                    <key>value</key>
                    <string>Untitled</string>
                </dict>
                <key>Position</key>
                <dict>
                    <key>value</key>
                    <string>{0.000,0.000}</string>
                </dict>
                <key>Scale</key>
                <dict>
                    <key>value</key>
                    <string>{1.000,1.000}</string>
                </dict>
                <key>Hidden</key>
                <dict>
                    <key>visible</key>
                    <string>0</string>
                </dict>
                <key>Locked</key>
                <dict>
                    <key>visible</key>
                    <string>0</string>
                </dict>
                <key>Stick To Edge</key>
                <dict>
                    <key>value</key>
                    <string>0</string>
                </dict>
                <key>zDepth</key>
                <string>0</string>
            </dict>
            <dict>
                <key>id</key>
                <string>1571</string>
                <key>className</key>
                <string>PTModelObjectImage</string>
                <key>Name</key>
                <dict>
                    <key>value</key>
                    <string>Untitled</string>
                </dict>
                <key>Position</key>
                <dict>
                    <key>value</key>
                    <string>{568.000,320.000}</string>
                </dict>
                <key>Scale</key>
                <dict>
                    <key>value</key>
                    <string>{1.000,1.000}</string>
                </dict>
                <key>Hidden</key>
                <dict>
                    <key>visible</key>
                    <string>0</string>
                </dict>
                <key>Locked</key>
                <dict>
                    <key>visible</key>
                    <string>0</string>
                </dict>
                <key>zDepth</key>
                <string>0</string>
            </dict>
            <dict>
                <key>id</key>
                <string>1579</string>
                <key>className</key>
                <string>PTModelObjectImage</string>
                <key>Name</key>
                <dict>
                    <key>value</key>
                    <string>Untitled</string>
                </dict>
                <key>Position</key>
                <dict>
                    <key>value</key>
                    <string>{569.763,321.763}</string>
                </dict>
                <key>Scale</key>
                <dict>
                    <key>value</key>
                    <string>{1.000,1.000}</string>
                </dict>
                <key>Hidden</key>
                <dict>
                    <key>visible</key>
                    <string>0</string>
                </dict>
                <key>Locked</key>
                <dict>
                    <key>visible</key>
                    <string>0</string>
                </dict>
                <key>zDepth</key>
                <string>0</string>
            </dict>
            <dict>
                <key>id</key>
                <string>1582</string>
                <key>className</key>
                <string>PTModelObjectImage</string>
                <key>Name</key>
                <dict>
                    <key>value</key>
                    <string>Game</string>
                </dict>
                <key>Position</key>
                <dict>
                    <key>value</key>
                    <string>{568.000,416.000}</string>
                </dict>
                <key>Scale</key>
                <dict>
                    <key>value</key>
                    <string>{1.000,1.000}</string>
                </dict>
                <key>Hidden</key>
                <dict>
                    <key>visible</key>
                    <string>0</string>
                </dict>
                <key>Locked</key>
                <dict>
                    <key>visible</key>
                    <string>0</string>
                </dict>
                <key>zDepth</key>
                <string>1</string>
            </dict>
            <dict>
                <key>id</key>
                <string>1586</string>
                <key>className</key>
                <string>PTModelObjectImage</string>
                <key>Name</key>
                <dict>
                    <key>value</key>
                    <string>Untitled</string>
                </dict>
                <key>Position</key>
                <dict>
                    <key>value</key>
                    <string>{568.000,320.000}</string>
                </dict>
                <key>Scale</key>
                <dict>
                    <key>value</key>
                    <string>{1.000,1.000}</string>
                </dict>
                <key>Hidden</key>
                <dict>
                    <key>visible</key>
                    <string>0</string>
                </dict>
                <key>Locked</key>
                <dict>
                    <key>visible</key>
                    <string>0</string>
                </dict>
                <key>zDepth</key>
                <string>0</string>
            </dict>
            <dict>
                <key>id</key>
                <string>1595</string>
                <key>className</key>
                <string>PTModelObjectImage</string>
                <key>Name</key>
                <dict>
                    <key>value</key>
                    <string>Untitled</string>
                </dict>
                <key>Position</key>
                <dict>
                    <key>value</key>
                    <string>{566.237,314.712}</string>
                </dict>
                <key>Scale</key>
                <dict>
                    <key>value</key>
                    <string>{1.000,1.000}</string>
                </dict>
                <key>Hidden</key>
                <dict>
                    <key>visible</key>
                    <string>0</string>
                </dict>
                <key>Locked</key>
                <dict>
                    <key>visible</key>
                    <string>0</string>
                </dict>
                <key>zDepth</key>
                <string>0</string>
            </dict>
            <dict>
                <key>id</key>
                <string>1602</string>
                <key>className</key>
                <string>PTModelObjectImage</string>
                <key>Name</key>
                <dict>
                    <key>value</key>
                    <string>Untitled</string>
                </dict>
                <key>Position</key>
                <dict>
                    <key>value</key>
                    <string>{564.475,325.288}</string>
                    <key>animationsX</key>
                    <array/>
                    <key>animationsY</key>
                    <array/>
                </dict>
                <key>Rotation</key>
                <dict>
                    <key>animations</key>
                    <array/>
                </dict>
                <key>Scale</key>
                <dict>
                    <key>value</key>
                    <string>{1.000,1.000}</string>
                    <key>animationsX</key>
                    <array/>
                    <key>animationsY</key>
                    <array/>
                </dict>
                <key>Hidden</key>
                <dict>
                    <key>visible</key>
                    <string>0</string>
                </dict>
                <key>Locked</key>
                <dict>
                    <key>visible</key>
                    <string>0</string>
                </dict>
                <key>zDepth</key>
                <string>0</string>
            </dict>
            <dict>
                <key>id</key>
                <string>1605</string>
                <key>className</key>
                <string>PTModelObjectImage</string>
                <key>Name</key>
                <dict>
                    <key>value</key>
                    <string>World Select</string>
                </dict>
                <key>Position</key>
                <dict>
                    <key>value</key>
                    <string>{578.576,512.000}</string>
                    <key>animationsX</key>
                    <array/>
                    <key>animationsY</key>
                    <array/>
                </dict>
                <key>Rotation</key>
                <dict>
                    <key>animations</key>
                    <array/>
                </dict>
                <key>Scale</key>
                <dict>
                    <key>value</key>
                    <string>{4.737,0.665}</string>
                    <key>animationsX</key>
                    <array/>
                    <key>animationsY</key>
                    <array/>
                </dict>
                <key>Hidden</key>
                <dict>
                    <key>visible</key>
                    <string>0</string>
                </dict>
                <key>Locked</key>
                <dict>
                    <key>visible</key>
                    <string>0</string>
                </dict>
                <key>zDepth</key>
                <string>1</string>
            </dict>
            <dict>
                <key>id</key>
                <string>1608</string>
                <key>className</key>
                <string>PTModelObjectImage</string>
                <key>Name</key>
                <dict>
                    <key>value</key>
                    <string>Untitled</string>
                </dict>
                <key>Position</key>
                <dict>
                    <key>value</key>
                    <string>{568.000,320.000}</string>
                </dict>
                <key>Scale</key>
                <dict>
                    <key>value</key>
                    <string>{1.000,1.000}</string>
                </dict>
                <key>Hidden</key>
                <dict>
                    <key>visible</key>
                    <string>0</string>
                </dict>
                <key>Locked</key>
                <dict>
                    <key>visible</key>
                    <string>0</string>
                </dict>
                <key>zDepth</key>
                <string>-1</string>
            </dict>
            <dict>
                <key>id</key>
                <string>1611</string>
                <key>className</key>
                <string>PTModelObjectImage</string>
                <key>Name</key>
                <dict>
                    <key>value</key>
                    <string>Logo</string>
                </dict>
                <key>Position</key>
                <dict>
                    <key>value</key>
                    <string>{268.500,525.500}</string>
                </dict>
                <key>Scale</key>
                <dict>
                    <key>value</key>
                    <string>{1.000,1.000}</string>
                </dict>
                <key>Hidden</key>
                <dict>
                    <key>visible</key>
                    <string>0</string>
                </dict>
                <key>Locked</key>
                <dict>
                    <key>visible</key>
                    <string>0</string>
                </dict>
                <key>zDepth</key>
                <string>0</string>
            </dict>
            <dict>
                <key>id</key>
                <string>1624</string>
                <key>className</key>
                <string>PTModelObjectImage</string>
                <key>Name</key>
                <dict>
                    <key>value</key>
                    <string>game over</string>
                </dict>
                <key>Position</key>
                <dict>
                    <key>value</key>
                    <string>{642.031,348.202}</string>
                </dict>
                <key>Scale</key>
                <dict>
                    <key>value</key>
                    <string>{1.000,1.000}</string>
                </dict>
                <key>Hidden</key>
                <dict>
                    <key>visible</key>
                    <string>0</string>
                </dict>
                <key>Locked</key>
                <dict>
                    <key>visible</key>
                    <string>0</string>
                </dict>
                <key>zDepth</key>
                <string>0</string>
            </dict>
            <dict>
                <key>id</key>
                <string>1657</string>
                <key>className</key>
                <string>PTModelObjectImage</string>
                <key>Name</key>
                <dict>
                    <key>value</key>
                    <string>Untitled</string>
                </dict>
                <key>Position</key>
                <dict>
                    <key>value</key>
                    <string>{569.763,320.000}</string>
                </dict>
                <key>Scale</key>
                <dict>
                    <key>value</key>
                    <string>{1.000,1.000}</string>
                </dict>
                <key>Hidden</key>
                <dict>
                    <key>visible</key>
                    <string>0</string>
                </dict>
                <key>Locked</key>
                <dict>
                    <key>visible</key>
                    <string>0</string>
                </dict>
                <key>zDepth</key>
                <string>0</string>
            </dict>
            <dict>
                <key>id</key>
                <string>1689</string>
                <key>className</key>
                <string>PTModelObjectImage</string>
                <key>Name</key>
                <dict>
                    <key>value</key>
                    <string>2</string>
                </dict>
                <key>Position</key>
                <dict>
                    <key>value</key>
                    <string>{0.000,0.000}</string>
                    <key>animationsX</key>
                    <array/>
                    <key>animationsY</key>
                    <array/>
                </dict>
                <key>Rotation</key>
                <dict>
                    <key>animations</key>
                    <array/>
                </dict>
                <key>Scale</key>
                <dict>
                    <key>value</key>
                    <string>{1.000,1.000}</string>
                    <key>animationsX</key>
                    <array/>
                    <key>animationsY</key>
                    <array/>
                </dict>
                <key>Hidden</key>
                <dict>
                    <key>visible</key>
                    <string>0</string>
                </dict>
                <key>Locked</key>
                <dict>
                    <key>visible</key>
                    <string>0</string>
                </dict>
                <key>Opacity</key>
                <dict>
                    <key>animations</key>
                    <array/>
                </dict>
                <key>Stick To Edge</key>
                <dict>
                    <key>value</key>
                    <string>0</string>
                </dict>
                <key>zDepth</key>
                <string>0</string>
            </dict>
            <dict>
                <key>id</key>
                <string>1725</string>
                <key>className</key>
                <string>PTModelObjectImage</string>
                <key>Name</key>
                <dict>
                    <key>value</key>
                    <string>Idle (10)</string>
                </dict>
                <key>Position</key>
                <dict>
                    <key>value</key>
                    <string>{0.000,0.000}</string>
                    <key>animationsX</key>
                    <array/>
                    <key>animationsY</key>
                    <array/>
                </dict>
                <key>Rotation</key>
                <dict>
                    <key>animations</key>
                    <array/>
                </dict>
                <key>Scale</key>
                <dict>
                    <key>value</key>
                    <string>{1.000,1.000}</string>
                    <key>animationsX</key>
                    <array/>
                    <key>animationsY</key>
                    <array/>
                </dict>
                <key>Hidden</key>
                <dict>
                    <key>visible</key>
                    <string>0</string>
                </dict>
                <key>Locked</key>
                <dict>
                    <key>visible</key>
                    <string>0</string>
                </dict>
                <key>Opacity</key>
                <dict>
                    <key>animations</key>
                    <array/>
                </dict>
                <key>Stick To Edge</key>
                <dict>
                    <key>value</key>
                    <string>0</string>
                </dict>
                <key>zDepth</key>
                <string>0</string>
            </dict>
            <dict>
                <key>id</key>
                <string>1755</string>
                <key>className</key>
                <string>PTModelObjectImage</string>
                <key>Name</key>
                <dict>
                    <key>value</key>
                    <string>Dead (10)</string>
                </dict>
                <key>Position</key>
                <dict>
                    <key>value</key>
                    <string>{0.000,0.000}</string>
                </dict>
                <key>Scale</key>
                <dict>
                    <key>value</key>
                    <string>{1.000,1.000}</string>
                </dict>
                <key>Hidden</key>
                <dict>
                    <key>visible</key>
                    <string>0</string>
                </dict>
                <key>Locked</key>
                <dict>
                    <key>visible</key>
                    <string>0</string>
                </dict>
                <key>Stick To Edge</key>
                <dict>
                    <key>value</key>
                    <string>0</string>
                </dict>
                <key>zDepth</key>
                <string>0</string>
            </dict>
            <dict>
                <key>id</key>
                <string>1782</string>
                <key>className</key>
                <string>PTModelObjectImage</string>
                <key>Name</key>
                <dict>
                    <key>value</key>
                    <string>Jump (10)</string>
                </dict>
                <key>Position</key>
                <dict>
                    <key>value</key>
                    <string>{0.000,0.000}</string>
                    <key>animationsX</key>
                    <array/>
                    <key>animationsY</key>
                    <array/>
                </dict>
                <key>Rotation</key>
                <dict>
                    <key>animations</key>
                    <array/>
                </dict>
                <key>Scale</key>
                <dict>
                    <key>value</key>
                    <string>{1.000,1.000}</string>
                    <key>animationsX</key>
                    <array/>
                    <key>animationsY</key>
                    <array/>
                </dict>
                <key>Hidden</key>
                <dict>
                    <key>visible</key>
                    <string>0</string>
                </dict>
                <key>Locked</key>
                <dict>
                    <key>visible</key>
                    <string>0</string>
                </dict>
                <key>Stick To Edge</key>
                <dict>
                    <key>value</key>
                    <string>0</string>
                </dict>
                <key>zDepth</key>
                <string>0</string>
            </dict>
            <dict>
                <key>id</key>
                <string>1804</string>
                <key>className</key>
                <string>PTModelObjectImage</string>
                <key>Name</key>
                <dict>
                    <key>value</key>
                    <string>Run (8)</string>
                </dict>
                <key>Position</key>
                <dict>
                    <key>value</key>
                    <string>{0.000,0.000}</string>
                    <key>animationsX</key>
                    <array/>
                    <key>animationsY</key>
                    <array/>
                </dict>
                <key>Rotation</key>
                <dict>
                    <key>animations</key>
                    <array/>
                </dict>
                <key>Scale</key>
                <dict>
                    <key>value</key>
                    <string>{1.000,1.000}</string>
                    <key>animationsX</key>
                    <array/>
                    <key>animationsY</key>
                    <array/>
                </dict>
                <key>Hidden</key>
                <dict>
                    <key>visible</key>
                    <string>0</string>
                </dict>
                <key>Locked</key>
                <dict>
                    <key>visible</key>
                    <string>0</string>
                </dict>
                <key>Stick To Edge</key>
                <dict>
                    <key>value</key>
                    <string>0</string>
                </dict>
                <key>zDepth</key>
                <string>0</string>
            </dict>
            <dict>
                <key>id</key>
                <string>1816</string>
                <key>className</key>
                <string>PTModelObjectImage</string>
                <key>Name</key>
                <dict>
                    <key>value</key>
                    <string>Shoot (3)</string>
                </dict>
                <key>Position</key>
                <dict>
                    <key>value</key>
                    <string>{0.000,0.000}</string>
                    <key>animationsX</key>
                    <array/>
                    <key>animationsY</key>
                    <array/>
                </dict>
                <key>Rotation</key>
                <dict>
                    <key>animations</key>
                    <array/>
                </dict>
                <key>Scale</key>
                <dict>
                    <key>value</key>
                    <string>{1.000,1.000}</string>
                    <key>animationsX</key>
                    <array/>
                    <key>animationsY</key>
                    <array/>
                </dict>
                <key>Hidden</key>
                <dict>
                    <key>visible</key>
                    <string>0</string>
                </dict>
                <key>Locked</key>
                <dict>
                    <key>visible</key>
                    <string>0</string>
                </dict>
                <key>Stick To Edge</key>
                <dict>
                    <key>value</key>
                    <string>0</string>
                </dict>
                <key>zDepth</key>
                <string>0</string>
            </dict>
            <dict>
                <key>id</key>
                <string>1824</string>
                <key>className</key>
                <string>PTModelObjectImage</string>
                <key>Name</key>
                <dict>
                    <key>value</key>
                    <string>Tree_2</string>
                </dict>
                <key>Position</key>
                <dict>
                    <key>value</key>
                    <string>{0.000,0.000}</string>
                    <key>animationsX</key>
                    <array/>
                    <key>animationsY</key>
                    <array/>
                </dict>
                <key>Rotation</key>
                <dict>
                    <key>animations</key>
                    <array/>
                </dict>
                <key>Scale</key>
                <dict>
                    <key>value</key>
                    <string>{1.000,1.000}</string>
                    <key>animationsX</key>
                    <array/>
                    <key>animationsY</key>
                    <array/>
                </dict>
                <key>Hidden</key>
                <dict>
                    <key>visible</key>
                    <string>0</string>
                </dict>
                <key>Locked</key>
                <dict>
                    <key>visible</key>
                    <string>0</string>
                </dict>
                <key>Stick To Edge</key>
                <dict>
                    <key>value</key>
                    <string>0</string>
                </dict>
                <key>zDepth</key>
                <string>0</string>
            </dict>
            <dict>
                <key>id</key>
                <string>1842</string>
                <key>className</key>
                <string>PTModelObjectImage</string>
                <key>Name</key>
                <dict>
                    <key>value</key>
                    <string>Stone</string>
                </dict>
                <key>Position</key>
                <dict>
                    <key>value</key>
                    <string>{0.000,0.000}</string>
                    <key>animationsX</key>
                    <array/>
                    <key>animationsY</key>
                    <array/>
                </dict>
                <key>Rotation</key>
                <dict>
                    <key>animations</key>
                    <array/>
                </dict>
                <key>Scale</key>
                <dict>
                    <key>value</key>
                    <string>{1.000,1.000}</string>
                    <key>animationsX</key>
                    <array/>
                    <key>animationsY</key>
                    <array/>
                </dict>
                <key>Hidden</key>
                <dict>
                    <key>visible</key>
                    <string>0</string>
                </dict>
                <key>Locked</key>
                <dict>
                    <key>visible</key>
                    <string>0</string>
                </dict>
                <key>Stick To Edge</key>
                <dict>
                    <key>value</key>
                    <string>0</string>
                </dict>
                <key>zDepth</key>
                <string>0</string>
            </dict>
            <dict>
                <key>id</key>
                <string>1873</string>
                <key>className</key>
                <string>PTModelObjectImage</string>
                <key>Name</key>
                <dict>
                    <key>value</key>
                    <string>Crate</string>
                </dict>
                <key>Position</key>
                <dict>
                    <key>value</key>
                    <string>{0.000,0.000}</string>
                    <key>animationsX</key>
                    <array/>
                    <key>animationsY</key>
                    <array/>
                </dict>
                <key>Rotation</key>
                <dict>
                    <key>animations</key>
                    <array/>
                </dict>
                <key>Scale</key>
                <dict>
                    <key>value</key>
                    <string>{1.000,1.000}</string>
                    <key>animationsX</key>
                    <array/>
                    <key>animationsY</key>
                    <array/>
                </dict>
                <key>Hidden</key>
                <dict>
                    <key>visible</key>
                    <string>0</string>
                </dict>
                <key>Locked</key>
                <dict>
                    <key>visible</key>
                    <string>0</string>
                </dict>
                <key>Opacity</key>
                <dict>
                    <key>animations</key>
                    <array/>
                </dict>
                <key>Stick To Edge</key>
                <dict>
                    <key>value</key>
                    <string>0</string>
                </dict>
                <key>zDepth</key>
                <string>0</string>
            </dict>
            <dict>
                <key>id</key>
                <string>1941</string>
                <key>className</key>
                <string>PTModelObjectImage</string>
                <key>Name</key>
                <dict>
                    <key>value</key>
                    <string>IceBox</string>
                </dict>
                <key>Position</key>
                <dict>
                    <key>value</key>
                    <string>{0.000,0.000}</string>
                    <key>animationsX</key>
                    <array/>
                    <key>animationsY</key>
                    <array/>
                </dict>
                <key>Rotation</key>
                <dict>
                    <key>animations</key>
                    <array/>
                </dict>
                <key>Scale</key>
                <dict>
                    <key>value</key>
                    <string>{1.000,1.000}</string>
                    <key>animationsX</key>
                    <array/>
                    <key>animationsY</key>
                    <array/>
                </dict>
                <key>Hidden</key>
                <dict>
                    <key>visible</key>
                    <string>0</string>
                </dict>
                <key>Locked</key>
                <dict>
                    <key>visible</key>
                    <string>0</string>
                </dict>
                <key>Stick To Edge</key>
                <dict>
                    <key>value</key>
                    <string>0</string>
                </dict>
                <key>zDepth</key>
                <string>0</string>
            </dict>
            <dict>
                <key>id</key>
                <string>2104</string>
                <key>className</key>
                <string>PTModelObjectImage</string>
                <key>Name</key>
                <dict>
                    <key>value</key>
                    <string>BirdFly_000</string>
                </dict>
                <key>Position</key>
                <dict>
                    <key>value</key>
                    <string>{0.000,0.000}</string>
                </dict>
                <key>Scale</key>
                <dict>
                    <key>value</key>
                    <string>{1.000,1.000}</string>
                </dict>
                <key>Hidden</key>
                <dict>
                    <key>visible</key>
                    <string>0</string>
                </dict>
                <key>Locked</key>
                <dict>
                    <key>visible</key>
                    <string>0</string>
                </dict>
                <key>Stick To Edge</key>
                <dict>
                    <key>value</key>
                    <string>0</string>
                </dict>
                <key>zDepth</key>
                <string>0</string>
            </dict>
            <dict>
                <key>id</key>
                <string>2137</string>
                <key>className</key>
                <string>PTModelObjectImage</string>
                <key>Name</key>
                <dict>
                    <key>value</key>
                    <string>BirdFly_000</string>
                </dict>
                <key>Position</key>
                <dict>
                    <key>value</key>
                    <string>{0.000,0.000}</string>
                </dict>
                <key>Scale</key>
                <dict>
                    <key>value</key>
                    <string>{1.000,1.000}</string>
                </dict>
                <key>Hidden</key>
                <dict>
                    <key>visible</key>
                    <string>0</string>
                </dict>
                <key>Locked</key>
                <dict>
                    <key>visible</key>
                    <string>0</string>
                </dict>
                <key>Stick To Edge</key>
                <dict>
                    <key>value</key>
                    <string>0</string>
                </dict>
                <key>zDepth</key>
                <string>0</string>
            </dict>
            <dict>
                <key>id</key>
                <string>2165</string>
                <key>className</key>
                <string>PTModelObjectImage</string>
                <key>Name</key>
                <dict>
                    <key>value</key>
                    <string>BirdFly_024</string>
                </dict>
                <key>Position</key>
                <dict>
                    <key>value</key>
                    <string>{0.000,0.000}</string>
                    <key>animationsX</key>
                    <array/>
                    <key>animationsY</key>
                    <array/>
                </dict>
                <key>Rotation</key>
                <dict>
                    <key>animations</key>
                    <array/>
                </dict>
                <key>Scale</key>
                <dict>
                    <key>value</key>
                    <string>{1.000,1.000}</string>
                    <key>animationsX</key>
                    <array/>
                    <key>animationsY</key>
                    <array/>
                </dict>
                <key>Hidden</key>
                <dict>
                    <key>visible</key>
                    <string>0</string>
                </dict>
                <key>Locked</key>
                <dict>
                    <key>visible</key>
                    <string>0</string>
                </dict>
                <key>Stick To Edge</key>
                <dict>
                    <key>value</key>
                    <string>0</string>
                </dict>
                <key>zDepth</key>
                <string>0</string>
            </dict>
            <dict>
                <key>id</key>
                <string>2209</string>
                <key>className</key>
                <string>PTModelObjectImage</string>
                <key>Name</key>
                <dict>
                    <key>value</key>
                    <string>image 1</string>
                </dict>
                <key>Position</key>
                <dict>
                    <key>value</key>
                    <string>{0.000,0.000}</string>
                    <key>animationsX</key>
                    <array/>
                    <key>animationsY</key>
                    <array/>
                </dict>
                <key>Rotation</key>
                <dict>
                    <key>animations</key>
                    <array/>
                </dict>
                <key>Scale</key>
                <dict>
                    <key>value</key>
                    <string>{1.000,1.000}</string>
                    <key>animationsX</key>
                    <array/>
                    <key>animationsY</key>
                    <array/>
                </dict>
                <key>Hidden</key>
                <dict>
                    <key>visible</key>
                    <string>0</string>
                </dict>
                <key>Locked</key>
                <dict>
                    <key>visible</key>
                    <string>0</string>
                </dict>
                <key>Opacity</key>
                <dict>
                    <key>animations</key>
                    <array/>
                </dict>
                <key>Stick To Edge</key>
                <dict>
                    <key>value</key>
                    <string>0</string>
                </dict>
                <key>zDepth</key>
                <string>0</string>
            </dict>
            <dict>
                <key>id</key>
                <string>2227</string>
                <key>className</key>
                <string>PTModelObjectImage</string>
                <key>Name</key>
                <dict>
                    <key>value</key>
                    <string>boat png</string>
                </dict>
                <key>Position</key>
                <dict>
                    <key>value</key>
                    <string>{0.000,0.000}</string>
                </dict>
                <key>Scale</key>
                <dict>
                    <key>value</key>
                    <string>{1.000,1.000}</string>
                </dict>
                <key>Hidden</key>
                <dict>
                    <key>visible</key>
                    <string>0</string>
                </dict>
                <key>Locked</key>
                <dict>
                    <key>visible</key>
                    <string>0</string>
                </dict>
                <key>zDepth</key>
                <string>0</string>
            </dict>
            <dict>
                <key>id</key>
                <string>2239</string>
                <key>className</key>
                <string>PTModelObjectImage</string>
                <key>Name</key>
                <dict>
                    <key>value</key>
                    <string>boat png</string>
                </dict>
                <key>Position</key>
                <dict>
                    <key>value</key>
                    <string>{0.000,0.000}</string>
                    <key>animationsX</key>
                    <array/>
                    <key>animationsY</key>
                    <array/>
                </dict>
                <key>Rotation</key>
                <dict>
                    <key>animations</key>
                    <array/>
                </dict>
                <key>Scale</key>
                <dict>
                    <key>value</key>
                    <string>{1.000,1.000}</string>
                    <key>animationsX</key>
                    <array/>
                    <key>animationsY</key>
                    <array/>
                </dict>
                <key>Hidden</key>
                <dict>
                    <key>visible</key>
                    <string>0</string>
                </dict>
                <key>Locked</key>
                <dict>
                    <key>visible</key>
                    <string>0</string>
                </dict>
                <key>Opacity</key>
                <dict>
                    <key>animations</key>
                    <array/>
                </dict>
                <key>Stick To Edge</key>
                <dict>
                    <key>value</key>
                    <string>0</string>
                </dict>
                <key>zDepth</key>
                <string>0</string>
            </dict>
            <dict>
                <key>id</key>
                <string>2380</string>
                <key>className</key>
                <string>PTModelObjectImage</string>
                <key>Name</key>
                <dict>
                    <key>value</key>
                    <string>Saw</string>
                </dict>
                <key>Position</key>
                <dict>
                    <key>value</key>
                    <string>{0.000,0.000}</string>
                    <key>animationsX</key>
                    <array/>
                    <key>animationsY</key>
                    <array/>
                </dict>
                <key>Rotation</key>
                <dict>
                    <key>animations</key>
                    <array/>
                </dict>
                <key>Scale</key>
                <dict>
                    <key>value</key>
                    <string>{1.000,1.000}</string>
                    <key>animationsX</key>
                    <array/>
                    <key>animationsY</key>
                    <array/>
                </dict>
                <key>Hidden</key>
                <dict>
                    <key>visible</key>
                    <string>0</string>
                </dict>
                <key>Locked</key>
                <dict>
                    <key>visible</key>
                    <string>0</string>
                </dict>
                <key>Stick To Edge</key>
                <dict>
                    <key>value</key>
                    <string>0</string>
                </dict>
                <key>zDepth</key>
                <string>0</string>
            </dict>
            <dict>
                <key>id</key>
                <string>2392</string>
                <key>className</key>
                <string>PTModelObjectImage</string>
                <key>Name</key>
                <dict>
                    <key>value</key>
                    <string>Saw</string>
                </dict>
                <key>Position</key>
                <dict>
                    <key>value</key>
                    <string>{0.000,0.000}</string>
                </dict>
                <key>Scale</key>
                <dict>
                    <key>value</key>
                    <string>{1.000,1.000}</string>
                </dict>
                <key>Hidden</key>
                <dict>
                    <key>visible</key>
                    <string>0</string>
                </dict>
                <key>Locked</key>
                <dict>
                    <key>visible</key>
                    <string>0</string>
                </dict>
                <key>Stick To Edge</key>
                <dict>
                    <key>value</key>
                    <string>0</string>
                </dict>
                <key>zDepth</key>
                <string>0</string>
            </dict>
            <dict>
                <key>id</key>
                <string>2479</string>
                <key>className</key>
                <string>PTModelObjectImage</string>
                <key>Name</key>
                <dict>
                    <key>value</key>
                    <string>Saw</string>
                </dict>
                <key>Position</key>
                <dict>
                    <key>value</key>
                    <string>{0.000,0.000}</string>
                    <key>animationsX</key>
                    <array/>
                    <key>animationsY</key>
                    <array/>
                </dict>
                <key>Rotation</key>
                <dict>
                    <key>animations</key>
                    <array/>
                </dict>
                <key>Scale</key>
                <dict>
                    <key>value</key>
                    <string>{1.000,1.000}</string>
                    <key>animationsX</key>
                    <array/>
                    <key>animationsY</key>
                    <array/>
                </dict>
                <key>Hidden</key>
                <dict>
                    <key>visible</key>
                    <string>0</string>
                </dict>
                <key>Locked</key>
                <dict>
                    <key>visible</key>
                    <string>0</string>
                </dict>
                <key>Stick To Edge</key>
                <dict>
                    <key>value</key>
                    <string>0</string>
                </dict>
                <key>zDepth</key>
                <string>0</string>
            </dict>
            <dict>
                <key>id</key>
                <string>2491</string>
                <key>className</key>
                <string>PTModelObjectImage</string>
                <key>Name</key>
                <dict>
                    <key>value</key>
                    <string>Mushroom_1</string>
                </dict>
                <key>Position</key>
                <dict>
                    <key>value</key>
                    <string>{0.000,0.000}</string>
                    <key>animationsX</key>
                    <array/>
                    <key>animationsY</key>
                    <array/>
                </dict>
                <key>Rotation</key>
                <dict>
                    <key>animations</key>
                    <array/>
                </dict>
                <key>Scale</key>
                <dict>
                    <key>value</key>
                    <string>{1.000,1.000}</string>
                    <key>animationsX</key>
                    <array/>
                    <key>animationsY</key>
                    <array/>
                </dict>
                <key>Hidden</key>
                <dict>
                    <key>visible</key>
                    <string>0</string>
                </dict>
                <key>Locked</key>
                <dict>
                    <key>visible</key>
                    <string>0</string>
                </dict>
                <key>Stick To Edge</key>
                <dict>
                    <key>value</key>
                    <string>0</string>
                </dict>
                <key>zDepth</key>
                <string>0</string>
            </dict>
            <dict>
                <key>id</key>
                <string>2696</string>
                <key>className</key>
                <string>PTModelObjectImage</string>
                <key>Name</key>
                <dict>
                    <key>value</key>
                    <string>Environment</string>
                </dict>
                <key>Position</key>
                <dict>
                    <key>value</key>
                    <string>{0.000,0.000}</string>
                    <key>animationsX</key>
                    <array/>
                    <key>animationsY</key>
                    <array/>
                </dict>
                <key>Rotation</key>
                <dict>
                    <key>animations</key>
                    <array/>
                </dict>
                <key>Scale</key>
                <dict>
                    <key>value</key>
                    <string>{1.000,1.000}</string>
                    <key>animationsX</key>
                    <array/>
                    <key>animationsY</key>
                    <array/>
                </dict>
                <key>Hidden</key>
                <dict>
                    <key>visible</key>
                    <string>0</string>
                </dict>
                <key>Locked</key>
                <dict>
                    <key>visible</key>
                    <string>0</string>
                </dict>
                <key>Stick To Edge</key>
                <dict>
                    <key>value</key>
                    <string>0</string>
                </dict>
                <key>zDepth</key>
                <string>0</string>
            </dict>
            <dict>
                <key>id</key>
                <string>2942</string>
                <key>className</key>
                <string>PTModelObjectImage</string>
                <key>Name</key>
                <dict>
                    <key>value</key>
                    <string>ladder8</string>
                </dict>
                <key>Position</key>
                <dict>
                    <key>value</key>
                    <string>{0.000,0.000}</string>
                    <key>animationsX</key>
                    <array/>
                    <key>animationsY</key>
                    <array/>
                </dict>
                <key>Rotation</key>
                <dict>
                    <key>animations</key>
                    <array/>
                </dict>
                <key>Scale</key>
                <dict>
                    <key>value</key>
                    <string>{1.000,1.000}</string>
                    <key>animationsX</key>
                    <array/>
                    <key>animationsY</key>
                    <array/>
                </dict>
                <key>Hidden</key>
                <dict>
                    <key>visible</key>
                    <string>0</string>
                </dict>
                <key>Locked</key>
                <dict>
                    <key>visible</key>
                    <string>0</string>
                </dict>
                <key>Stick To Edge</key>
                <dict>
                    <key>value</key>
                    <string>0</string>
                </dict>
                <key>zDepth</key>
                <string>0</string>
            </dict>
            <dict>
                <key>id</key>
                <string>2979</string>
                <key>className</key>
                <string>PTModelObjectImage</string>
                <key>Name</key>
                <dict>
                    <key>value</key>
                    <string>coin1</string>
                </dict>
                <key>Position</key>
                <dict>
                    <key>value</key>
                    <string>{0.000,0.000}</string>
                    <key>animationsX</key>
                    <array/>
                    <key>animationsY</key>
                    <array/>
                </dict>
                <key>Rotation</key>
                <dict>
                    <key>animations</key>
                    <array/>
                </dict>
                <key>Scale</key>
                <dict>
                    <key>value</key>
                    <string>{1.000,1.000}</string>
                    <key>animationsX</key>
                    <array/>
                    <key>animationsY</key>
                    <array/>
                </dict>
                <key>Hidden</key>
                <dict>
                    <key>visible</key>
                    <string>0</string>
                </dict>
                <key>Locked</key>
                <dict>
                    <key>visible</key>
                    <string>0</string>
                </dict>
                <key>Opacity</key>
                <dict>
                    <key>animations</key>
                    <array/>
                </dict>
                <key>Stick To Edge</key>
                <dict>
                    <key>value</key>
                    <string>0</string>
                </dict>
                <key>zDepth</key>
                <string>0</string>
            </dict>
            <dict>
                <key>id</key>
                <string>3211</string>
                <key>className</key>
                <string>PTModelObjectImage</string>
                <key>Name</key>
                <dict>
                    <key>value</key>
                    <string>start</string>
                </dict>
                <key>Position</key>
                <dict>
                    <key>value</key>
                    <string>{571.093,317.274}</string>
                    <key>animationsX</key>
                    <array/>
                    <key>animationsY</key>
                    <array/>
                </dict>
                <key>Rotation</key>
                <dict>
                    <key>animations</key>
                    <array/>
                </dict>
                <key>Scale</key>
                <dict>
                    <key>value</key>
                    <string>{3.644,3.859}</string>
                    <key>animationsX</key>
                    <array/>
                    <key>animationsY</key>
                    <array/>
                </dict>
                <key>Hidden</key>
                <dict>
                    <key>visible</key>
                    <string>0</string>
                </dict>
                <key>Locked</key>
                <dict>
                    <key>visible</key>
                    <string>0</string>
                </dict>
                <key>zDepth</key>
                <string>0</string>
            </dict>
            <dict>
                <key>id</key>
                <string>3319</string>
                <key>className</key>
                <string>PTModelObjectImage</string>
                <key>Name</key>
                <dict>
                    <key>value</key>
                    <string>Untitled 3</string>
                </dict>
                <key>Position</key>
                <dict>
                    <key>value</key>
                    <string>{1064.631,562.280}</string>
                    <key>animationsX</key>
                    <array/>
                    <key>animationsY</key>
                    <array/>
                </dict>
                <key>Rotation</key>
                <dict>
                    <key>animations</key>
                    <array/>
                </dict>
                <key>Scale</key>
                <dict>
                    <key>value</key>
                    <string>{0.614,0.688}</string>
                    <key>animationsX</key>
                    <array/>
                    <key>animationsY</key>
                    <array/>
                </dict>
                <key>Hidden</key>
                <dict>
                    <key>visible</key>
                    <string>0</string>
                </dict>
                <key>Locked</key>
                <dict>
                    <key>visible</key>
                    <string>0</string>
                </dict>
                <key>zDepth</key>
                <string>8</string>
            </dict>
            <dict>
                <key>id</key>
                <string>3496</string>
                <key>className</key>
                <string>PTModelObjectImage</string>
                <key>Name</key>
                <dict>
                    <key>value</key>
                    <string>Saw</string>
                </dict>
                <key>Position</key>
                <dict>
                    <key>value</key>
                    <string>{0.000,0.000}</string>
                </dict>
                <key>Scale</key>
                <dict>
                    <key>value</key>
                    <string>{1.000,1.000}</string>
                </dict>
                <key>Hidden</key>
                <dict>
                    <key>visible</key>
                    <string>0</string>
                </dict>
                <key>Locked</key>
                <dict>
                    <key>visible</key>
                    <string>0</string>
                </dict>
                <key>Stick To Edge</key>
                <dict>
                    <key>value</key>
                    <string>0</string>
                </dict>
                <key>zDepth</key>
                <string>0</string>
            </dict>
            <dict>
                <key>id</key>
                <string>3648</string>
                <key>className</key>
                <string>PTModelObjectImage</string>
                <key>Name</key>
                <dict>
                    <key>value</key>
                    <string>Saw</string>
                </dict>
                <key>Position</key>
                <dict>
                    <key>value</key>
                    <string>{0.000,0.000}</string>
                    <key>animationsX</key>
                    <array/>
                    <key>animationsY</key>
                    <array/>
                </dict>
                <key>Rotation</key>
                <dict>
                    <key>animations</key>
                    <array/>
                </dict>
                <key>Scale</key>
                <dict>
                    <key>value</key>
                    <string>{1.000,1.000}</string>
                    <key>animationsX</key>
                    <array/>
                    <key>animationsY</key>
                    <array/>
                </dict>
                <key>Hidden</key>
                <dict>
                    <key>visible</key>
                    <string>0</string>
                </dict>
                <key>Locked</key>
                <dict>
                    <key>visible</key>
                    <string>0</string>
                </dict>
                <key>Stick To Edge</key>
                <dict>
                    <key>value</key>
                    <string>0</string>
                </dict>
                <key>zDepth</key>
                <string>0</string>
            </dict>
            <dict>
                <key>id</key>
                <string>4330</string>
                <key>className</key>
                <string>PTModelObjectImage</string>
                <key>Name</key>
                <dict>
                    <key>value</key>
                    <string>Untitled 2</string>
                </dict>
                <key>Position</key>
                <dict>
                    <key>value</key>
                    <string>{569.330,315.512}</string>
                </dict>
                <key>Scale</key>
                <dict>
                    <key>value</key>
                    <string>{3.633,3.988}</string>
                </dict>
                <key>Hidden</key>
                <dict>
                    <key>visible</key>
                    <string>0</string>
                </dict>
                <key>Locked</key>
                <dict>
                    <key>visible</key>
                    <string>0</string>
                </dict>
                <key>zDepth</key>
                <string>2</string>
            </dict>
            <dict>
                <key>id</key>
                <string>4335</string>
                <key>className</key>
                <string>PTModelObjectImage</string>
                <key>Name</key>
                <dict>
                    <key>value</key>
                    <string>Untitled 2</string>
                </dict>
                <key>Position</key>
                <dict>
                    <key>value</key>
                    <string>{565.805,320.800}</string>
                </dict>
                <key>Scale</key>
                <dict>
                    <key>value</key>
                    <string>{3.655,3.773}</string>
                </dict>
                <key>Hidden</key>
                <dict>
                    <key>visible</key>
                    <string>0</string>
                </dict>
                <key>Locked</key>
                <dict>
                    <key>visible</key>
                    <string>0</string>
                </dict>
                <key>zDepth</key>
                <string>2</string>
            </dict>
            <dict>
                <key>id</key>
                <string>4383</string>
                <key>className</key>
                <string>PTModelObjectImage</string>
                <key>Name</key>
                <dict>
                    <key>value</key>
                    <string>main menu</string>
                </dict>
                <key>Position</key>
                <dict>
                    <key>value</key>
                    <string>{905.994,375.441}</string>
                </dict>
                <key>Scale</key>
                <dict>
                    <key>value</key>
                    <string>{1.956,0.452}</string>
                </dict>
                <key>Hidden</key>
                <dict>
                    <key>visible</key>
                    <string>0</string>
                </dict>
                <key>Locked</key>
                <dict>
                    <key>visible</key>
                    <string>0</string>
                </dict>
                <key>zDepth</key>
                <string>3</string>
            </dict>
            <dict>
                <key>id</key>
                <string>4389</string>
                <key>className</key>
                <string>PTModelObjectImage</string>
                <key>Name</key>
                <dict>
                    <key>value</key>
                    <string>Untitled</string>
                </dict>
                <key>Position</key>
                <dict>
                    <key>value</key>
                    <string>{907.757,227.380}</string>
                </dict>
                <key>Scale</key>
                <dict>
                    <key>value</key>
                    <string>{2.234,0.559}</string>
                </dict>
                <key>Hidden</key>
                <dict>
                    <key>visible</key>
                    <string>0</string>
                </dict>
                <key>Locked</key>
                <dict>
                    <key>visible</key>
                    <string>0</string>
                </dict>
                <key>zDepth</key>
                <string>4</string>
            </dict>
            <dict>
                <key>id</key>
                <string>4394</string>
                <key>className</key>
                <string>PTModelObjectImage</string>
                <key>Name</key>
                <dict>
                    <key>value</key>
                    <string>Untitled 2</string>
                </dict>
                <key>Position</key>
                <dict>
                    <key>value</key>
                    <string>{571.093,317.274}</string>
                </dict>
                <key>Scale</key>
                <dict>
                    <key>value</key>
                    <string>{1.000,0.633}</string>
                </dict>
                <key>Hidden</key>
                <dict>
                    <key>visible</key>
                    <string>0</string>
                </dict>
                <key>Locked</key>
                <dict>
                    <key>visible</key>
                    <string>0</string>
                </dict>
                <key>zDepth</key>
                <string>2</string>
            </dict>
            <dict>
                <key>id</key>
                <string>4399</string>
                <key>className</key>
                <string>PTModelObjectImage</string>
                <key>Name</key>
                <dict>
                    <key>value</key>
                    <string>Untitled 2</string>
                </dict>
                <key>Position</key>
                <dict>
                    <key>value</key>
                    <string>{565.806,320.799}</string>
                </dict>
                <key>Scale</key>
                <dict>
                    <key>value</key>
                    <string>{1.000,0.553}</string>
                </dict>
                <key>Hidden</key>
                <dict>
                    <key>visible</key>
                    <string>0</string>
                </dict>
                <key>Locked</key>
                <dict>
                    <key>visible</key>
                    <string>0</string>
                </dict>
                <key>zDepth</key>
                <string>2</string>
            </dict>
            <dict>
                <key>id</key>
                <string>4404</string>
                <key>className</key>
                <string>PTModelObjectImage</string>
                <key>Name</key>
                <dict>
                    <key>value</key>
                    <string>Untitled 2</string>
                </dict>
                <key>Position</key>
                <dict>
                    <key>value</key>
                    <string>{576.381,410.694}</string>
                </dict>
                <key>Scale</key>
                <dict>
                    <key>value</key>
                    <string>{1.000,1.762}</string>
                </dict>
                <key>Hidden</key>
                <dict>
                    <key>visible</key>
                    <string>0</string>
                </dict>
                <key>Locked</key>
                <dict>
                    <key>visible</key>
                    <string>0</string>
                </dict>
                <key>zDepth</key>
                <string>5</string>
            </dict>
            <dict>
                <key>id</key>
                <string>4409</string>
                <key>className</key>
                <string>PTModelObjectImage</string>
                <key>Name</key>
                <dict>
                    <key>value</key>
                    <string>Untitled 3</string>
                </dict>
                <key>Position</key>
                <dict>
                    <key>value</key>
                    <string>{571.093,169.213}</string>
                </dict>
                <key>Scale</key>
                <dict>
                    <key>value</key>
                    <string>{1.458,0.807}</string>
                </dict>
                <key>Hidden</key>
                <dict>
                    <key>visible</key>
                    <string>0</string>
                </dict>
                <key>Locked</key>
                <dict>
                    <key>visible</key>
                    <string>0</string>
                </dict>
                <key>zDepth</key>
                <string>6</string>
            </dict>
            <dict>
                <key>id</key>
                <string>4414</string>
                <key>className</key>
                <string>PTModelObjectImage</string>
                <key>Name</key>
                <dict>
                    <key>value</key>
                    <string>Untitled 4</string>
                </dict>
                <key>Position</key>
                <dict>
                    <key>value</key>
                    <string>{1024.090,546.417}</string>
                </dict>
                <key>Scale</key>
                <dict>
                    <key>value</key>
                    <string>{0.373,0.232}</string>
                </dict>
                <key>Hidden</key>
                <dict>
                    <key>visible</key>
                    <string>0</string>
                </dict>
                <key>Locked</key>
                <dict>
                    <key>visible</key>
                    <string>0</string>
                </dict>
                <key>zDepth</key>
                <string>7</string>
            </dict>
            <dict>
                <key>id</key>
                <string>4419</string>
                <key>className</key>
                <string>PTModelObjectImage</string>
                <key>Name</key>
                <dict>
                    <key>value</key>
                    <string>Untitled 5</string>
                </dict>
                <key>Position</key>
                <dict>
                    <key>value</key>
                    <string>{102.233,541.129}</string>
                </dict>
                <key>Scale</key>
                <dict>
                    <key>value</key>
                    <string>{0.624,0.499}</string>
                </dict>
                <key>Hidden</key>
                <dict>
                    <key>visible</key>
                    <string>0</string>
                </dict>
                <key>Locked</key>
                <dict>
                    <key>visible</key>
                    <string>0</string>
                </dict>
                <key>zDepth</key>
                <string>8</string>
            </dict>
            <dict>
                <key>id</key>
                <string>4424</string>
                <key>className</key>
                <string>PTModelObjectImage</string>
                <key>Name</key>
                <dict>
                    <key>value</key>
                    <string>Untitled 2</string>
                </dict>
                <key>Position</key>
                <dict>
                    <key>value</key>
                    <string>{320.799,354.289}</string>
                    <key>animationsX</key>
                    <array/>
                    <key>animationsY</key>
                    <array/>
                </dict>
                <key>Rotation</key>
                <dict>
                    <key>animations</key>
                    <array/>
                </dict>
                <key>Scale</key>
                <dict>
                    <key>value</key>
                    <string>{0.436,0.436}</string>
                    <key>animationsX</key>
                    <array/>
                    <key>animationsY</key>
                    <array/>
                </dict>
                <key>Hidden</key>
                <dict>
                    <key>visible</key>
                    <string>0</string>
                </dict>
                <key>Locked</key>
                <dict>
                    <key>visible</key>
                    <string>0</string>
                </dict>
                <key>zDepth</key>
                <string>4</string>
            </dict>
            <dict>
                <key>id</key>
                <string>4430</string>
                <key>className</key>
                <string>PTModelObjectImage</string>
                <key>Name</key>
                <dict>
                    <key>value</key>
                    <string>Untitled 3</string>
                </dict>
                <key>Position</key>
                <dict>
                    <key>value</key>
                    <string>{491.775,352.527}</string>
                    <key>animationsX</key>
                    <array/>
                    <key>animationsY</key>
                    <array/>
                </dict>
                <key>Rotation</key>
                <dict>
                    <key>animations</key>
                    <array/>
                </dict>
                <key>Scale</key>
                <dict>
                    <key>value</key>
                    <string>{0.405,0.467}</string>
                    <key>animationsX</key>
                    <array/>
                    <key>animationsY</key>
                    <array/>
                </dict>
                <key>Hidden</key>
                <dict>
                    <key>visible</key>
                    <string>0</string>
                </dict>
                <key>Locked</key>
                <dict>
                    <key>visible</key>
                    <string>0</string>
                </dict>
                <key>zDepth</key>
                <string>5</string>
            </dict>
            <dict>
                <key>id</key>
                <string>4435</string>
                <key>className</key>
                <string>PTModelObjectImage</string>
                <key>Name</key>
                <dict>
                    <key>value</key>
                    <string>Untitled 4</string>
                </dict>
                <key>Position</key>
                <dict>
                    <key>value</key>
                    <string>{382.492,88.132}</string>
                    <key>animationsX</key>
                    <array/>
                    <key>animationsY</key>
                    <array/>
                </dict>
                <key>Rotation</key>
                <dict>
                    <key>animations</key>
                    <array/>
                </dict>
                <key>Scale</key>
                <dict>
                    <key>value</key>
                    <string>{1.000,0.426}</string>
                    <key>animationsX</key>
                    <array/>
                    <key>animationsY</key>
                    <array/>
                </dict>
                <key>Hidden</key>
                <dict>
                    <key>visible</key>
                    <string>0</string>
                </dict>
                <key>Locked</key>
                <dict>
                    <key>visible</key>
                    <string>0</string>
                </dict>
                <key>zDepth</key>
                <string>6</string>
            </dict>
        </array>
    </dict>
</plist>
